pytransit/__init__.py
pytransit/limb_darkening.py
pytransit/contamination/__init__.py
pytransit/contamination/contamination.py
pytransit/contamination/filter.py
pytransit/contamination/instrument.py
pytransit/contamination/plotting.py
pytransit/contamination/data/spectra.h5
pytransit/contamination/data/transmission.nc
pytransit/lpf/__init__.py
pytransit/lpf/cntlpf.py
pytransit/lpf/eclipselpf.py
pytransit/lpf/logposteriorfunction.py
pytransit/lpf/lpf.py
pytransit/lpf/mclpf.py
pytransit/lpf/mptlpf.py
pytransit/lpf/ocllpf.py
pytransit/lpf/ocltdvlpf.py
pytransit/lpf/oclttvlpf.py
pytransit/lpf/phasecurvelpf.py
pytransit/lpf/rvlpf.py
pytransit/lpf/tdvlpf.py
pytransit/lpf/tesslpf.py
pytransit/lpf/tessoclttvlpf.py
pytransit/lpf/transitanalysis.py
pytransit/lpf/transitlpf.py
pytransit/lpf/ttvlpf.py
pytransit/lpf/baselines/__init__.py
pytransit/lpf/baselines/legendrebaseline.py
pytransit/lpf/baselines/linearbaseline.py
pytransit/lpf/loglikelihood/__init__.py
pytransit/lpf/loglikelihood/celeriteloglikelihood.py
pytransit/lpf/loglikelihood/clloglikelihood.py
pytransit/lpf/loglikelihood/fmcloglikelihood.py
pytransit/lpf/loglikelihood/logisticloglikelihood.py
pytransit/lpf/loglikelihood/multiceleriteloglikelihood.py
pytransit/lpf/loglikelihood/wnloglikelihood.py
pytransit/lpf/tess/__init__.py
pytransit/lpf/tess/ctesslpf.py
pytransit/lpf/tess/tessttvlpf.py
pytransit/lpf/tess/tgclpf.py
pytransit/lpf/tess/tgcmplpf.py
pytransit/lpf/tess/tmpclpf.py
pytransit/models/__init__.py
pytransit/models/eclipse_model.py
pytransit/models/gdmodel.py
pytransit/models/general.py
pytransit/models/ldmodel.py
pytransit/models/ldtkldm.py
pytransit/models/ma_chromosphere.py
pytransit/models/ma_quadratic.py
pytransit/models/ma_quadratic_cl.py
pytransit/models/ma_uniform.py
pytransit/models/ma_uniform_cl.py
pytransit/models/osmodel.py
pytransit/models/qpower2.py
pytransit/models/qpower2_cl.py
pytransit/models/transitmodel.py
pytransit/models/uniform.py
pytransit/models/limb_darkening/__init__.py
pytransit-2.6.14.dist-info/licenses/LICENSE
pytransit-2.6.14.dist-info/METADATA
pytransit-2.6.14.dist-info/WHEEL
pytransit-2.6.14.dist-info/top_level.txt
pytransit-2.6.14.dist-info/RECORD
