Metadata-Version: 2.4
Name: PyTransit
Version: 2.6.14
Summary: Fast and painless exoplanet transit light curve modelling.
Author-email: Hannu Parviainen <hpparvi@gmail.com>
License: GPLv2
Project-URL: homepage, https://github.com/hpparvi/PyTransit
Keywords: astronomy,astrophysics,exoplanets
Classifier: Topic :: Scientific/Engineering
Classifier: Intended Audience :: Science/Research
Classifier: Intended Audience :: Developers
Classifier: Development Status :: 5 - Production/Stable
Classifier: License :: OSI Approved :: GNU General Public License v2 (GPLv2)
Classifier: Operating System :: OS Independent
Classifier: Programming Language :: Python
Requires-Python: >=3.10
License-File: LICENSE
Requires-Dist: arviz
Requires-Dist: numpy
Requires-Dist: scipy
Requires-Dist: pandas
Requires-Dist: xarray
Requires-Dist: tables
Requires-Dist: uncertainties
Requires-Dist: numba
Requires-Dist: astropy
Requires-Dist: matplotlib
Requires-Dist: tqdm
Requires-Dist: semantic_version
Requires-Dist: setuptools
Requires-Dist: deprecated
Requires-Dist: seaborn
Requires-Dist: emcee
Requires-Dist: pyopencl
Requires-Dist: corner
Requires-Dist: celerite
Requires-Dist: meepmeep
Dynamic: license-file
